twaml/__init__.py
twaml/_apps.py
twaml/data.py
twaml/pytorch.py
twaml/utils.py
twaml/version.py
twaml/viz.py
twaml-0.10.0.dist-info/LICENSE
twaml-0.10.0.dist-info/METADATA
twaml-0.10.0.dist-info/WHEEL
twaml-0.10.0.dist-info/entry_points.txt
twaml-0.10.0.dist-info/top_level.txt
twaml-0.10.0.dist-info/RECORD
