Metadata-Version: 2.1
Name: twaml
Version: 0.10.0
Summary: tW Analysis Machine Learning
Home-page: https://github.com/drdavis/twaml
Author: Doug Davis
Author-email: ddavis@ddavis.io
License: MIT
Platform: UNKNOWN
Classifier: Development Status :: 3 - Alpha
Classifier: Intended Audience :: Science/Research
Classifier: Programming Language :: Python :: 3.6
Classifier: Programming Language :: Python :: 3.7
Requires-Python: >3.6.5
Requires-Dist: pyyaml (>=5.1)
Requires-Dist: uproot (>=3.0)
Requires-Dist: matplotlib (>=3.0)
Requires-Dist: pandas (>=0.24.0)
Requires-Dist: scikit-learn (>=0.20)
Requires-Dist: tables (>=3.4)
Requires-Dist: numexpr (>=2.6.5)
Requires-Dist: h5py (>=2.8.0)
Requires-Dist: lz4 (>=2.1.5)
